lob/__init__.py
lob/api_requestor.py
lob/compat.py
lob/error.py
lob/resource.py
lob/version.py
lob-4.0.1.dist-info/LICENSE
lob-4.0.1.dist-info/METADATA
lob-4.0.1.dist-info/WHEEL
lob-4.0.1.dist-info/top_level.txt
lob-4.0.1.dist-info/RECORD
